{
  "table_id": "TBL-DOC-POL-009-026",
  "document_id": "DOC-POL-009",
  "page_no_or_sheet_name": "section7",
  "block_order": 132,
  "table_title": "",
  "header_rows": [
    1
  ],
  "table_shape": {
    "rows": 2,
    "cols": 2
  },
  "cell_matrix": [
    [
      "",
      ""
    ],
    [
      "< Nature Index TOP 200 연구기관 수 >",
      "< 주요국 상위 10개 기관의 평균 순위 추세 >"
    ]
  ],
  "merged_cell_info": [],
  "source_bbox": null,
  "extraction_confidence": "high",
  "extraction_method": "hwpx-xml-parser",
  "paragraph_id": "2147483648",
  "source_table_id": "2027747706",
  "repeat_header": "1",
  "treat_as_char": "1",
  "text_wrap": "TOP_AND_BOTTOM"
}