{
  "table_id": "TBL-DOC-POL-002-060",
  "document_id": "DOC-POL-002",
  "page_no_or_sheet_name": "section7",
  "block_order": 233,
  "table_title": "",
  "header_rows": [
    1
  ],
  "table_shape": {
    "rows": 3,
    "cols": 3
  },
  "cell_matrix": [
    [
      "",
      "✔ 해외 사례",
      ""
    ],
    [
      "",
      "",
      ""
    ],
    [
      "• 미국은 AI 영상분석 소프트웨어에 대해 신의료기술로 인정시 기존 수가 비용 이외에 최대 3년간 별도 보상 제공",
      "",
      ""
    ]
  ],
  "merged_cell_info": [
    {
      "row_index": 0,
      "col_index": 1,
      "row_span": 2,
      "col_span": 1
    },
    {
      "row_index": 2,
      "col_index": 0,
      "row_span": 1,
      "col_span": 3
    }
  ],
  "source_bbox": null,
  "extraction_confidence": "high",
  "extraction_method": "hwpx-xml-parser",
  "paragraph_id": "2147483648",
  "source_table_id": "2021971434",
  "repeat_header": "1",
  "treat_as_char": "1",
  "text_wrap": "TOP_AND_BOTTOM"
}