[
  {
    "evidence_id": "EVD-DOC-CTX-005-00001",
    "document_id": "DOC-CTX-005",
    "page_no_or_sheet_name": 1,
    "block_order": 1,
    "block_type": "text_block",
    "text": "<세부 기술(정책) 분류체계>",
    "bbox": [
      221.0402069091797,
      91.03954315185547,
      371.2165832519531,
      102.05646514892578
    ],
    "extraction_method": "pymupdf-text-dict-sort",
    "extraction_confidence": "high",
    "page_no": 1
  },
  {
    "evidence_id": "EVD-DOC-CTX-005-00002",
    "document_id": "DOC-CTX-005",
    "page_no_or_sheet_name": 1,
    "block_order": 2,
    "block_type": "text_block",
    "text": "대분류\n중분류\n기술 개요",
    "bbox": [
      83.59469604492188,
      118.01007080078125,
      390.841064453125,
      129.02699279785156
    ],
    "extraction_method": "pymupdf-text-dict-sort",
    "extraction_confidence": "high",
    "page_no": 1
  },
  {
    "evidence_id": "EVD-DOC-CTX-005-00003",
    "document_id": "DOC-CTX-005",
    "page_no_or_sheet_name": 1,
    "block_order": 3,
    "block_type": "text_block",
    "text": "재생에너지\n태양광, 풍력 등 재생에너지 변환·이용 및 원자력 활용 전력 생산 전\n주기 기술",
    "bbox": [
      149.1991424560547,
      145.9624481201172,
      519.8961181640625,
      168.84747314453125
    ],
    "extraction_method": "pymupdf-text-dict-sort",
    "extraction_confidence": "high",
    "page_no": 1
  },
  {
    "evidence_id": "EVD-DOC-CTX-005-00004",
    "document_id": "DOC-CTX-005",
    "page_no_or_sheet_name": 1,
    "block_order": 4,
    "block_type": "text_block",
    "text": "전력망\n전기에너지를 안정적으로 공급･ 소비하기 위한 전력망, 에너지저장장\n치(ESS) 등 전력기기 제반 기술",
    "bbox": [
      158.6739959716797,
      185.5703887939453,
      520.0145263671875,
      208.76385498046875
    ],
    "extraction_method": "pymupdf-text-dict-sort",
    "extraction_confidence": "high",
    "page_no": 1
  },
  {
    "evidence_id": "EVD-DOC-CTX-005-00005",
    "document_id": "DOC-CTX-005",
    "page_no_or_sheet_name": 1,
    "block_order": 5,
    "block_type": "text_block",
    "text": "에너지믹스",
    "bbox": [
      75.07930755615234,
      199.3041534423828,
      122.67018127441406,
      209.2433319091797
    ],
    "extraction_method": "pymupdf-text-dict-sort",
    "extraction_confidence": "high",
    "page_no": 1
  },
  {
    "evidence_id": "EVD-DOC-CTX-005-00006",
    "document_id": "DOC-CTX-005",
    "page_no_or_sheet_name": 1,
    "block_order": 6,
    "block_type": "text_block",
    "text": "수소\n청정수소의 생산, 저장 및 운송에서 활용까지의 전주기 기술",
    "bbox": [
      163.47140502929688,
      225.79519653320312,
      480.9169006347656,
      235.734375
    ],
    "extraction_method": "pymupdf-text-dict-sort",
    "extraction_confidence": "high",
    "page_no": 1
  },
  {
    "evidence_id": "EVD-DOC-CTX-005-00007",
    "document_id": "DOC-CTX-005",
    "page_no_or_sheet_name": 1,
    "block_order": 7,
    "block_type": "text_block",
    "text": "원자력\n원자력(핵분열) 활용 전력 생산을 위한 발전 전주기 기술",
    "bbox": [
      158.6739959716797,
      252.76573181152344,
      465.6851806640625,
      262.7049255371094
    ],
    "extraction_method": "pymupdf-text-dict-sort",
    "extraction_confidence": "high",
    "page_no": 1
  },
  {
    "evidence_id": "EVD-DOC-CTX-005-00008",
    "document_id": "DOC-CTX-005",
    "page_no_or_sheet_name": 1,
    "block_order": 8,
    "block_type": "text_block",
    "text": "산업공정\n배출집약적 4대 주력산업(철강, 석유화학, 시멘트, 반도체·디스플레이)\n과 산업 전반의 탄소중립을 위한 제반 기술",
    "bbox": [
      153.9965362548828,
      279.73626708984375,
      519.8663940429688,
      302.6213073730469
    ],
    "extraction_method": "pymupdf-text-dict-sort",
    "extraction_confidence": "high",
    "page_no": 1
  },
  {
    "evidence_id": "EVD-DOC-CTX-005-00009",
    "document_id": "DOC-CTX-005",
    "page_no_or_sheet_name": 1,
    "block_order": 9,
    "block_type": "text_block",
    "text": "저탄소산업",
    "bbox": [
      75.07930755615234,
      332.5984802246094,
      122.67018127441406,
      342.53765869140625
    ],
    "extraction_method": "pymupdf-text-dict-sort",
    "extraction_confidence": "high",
    "page_no": 1
  },
  {
    "evidence_id": "EVD-DOC-CTX-005-00010",
    "document_id": "DOC-CTX-005",
    "page_no_or_sheet_name": 1,
    "block_order": 10,
    "block_type": "text_block",
    "text": "CCUS",
    "bbox": [
      161.0727081298828,
      332.5984802246094,
      184.91659545898438,
      342.53765869140625
    ],
    "extraction_method": "pymupdf-text-dict-sort",
    "extraction_confidence": "high",
    "page_no": 1
  },
  {
    "evidence_id": "EVD-DOC-CTX-005-00011",
    "document_id": "DOC-CTX-005",
    "page_no_or_sheet_name": 1,
    "block_order": 11,
    "block_type": "text_block",
    "text": "에너지 변환, 산업공정 과정 중 배출되는 CO2를 포집한 후 심부 지\n층에 안전하게 저장하거나 유용한 전환과정을 통해 제품으로 활용하\n는 기술",
    "bbox": [
      217.92189025878906,
      319.65264892578125,
      520.0160522460938,
      355.4835205078125
    ],
    "extraction_method": "pymupdf-text-dict-sort",
    "extraction_confidence": "high",
    "page_no": 1
  },
  {
    "evidence_id": "EVD-DOC-CTX-005-00012",
    "document_id": "DOC-CTX-005",
    "page_no_or_sheet_name": 1,
    "block_order": 12,
    "block_type": "text_block",
    "text": "효율수요관리\n에너지 수요관리 최적화 및 3대 소비(산업, 건물, 수송 등) 부문의 에\n너지 효율 향상 기술",
    "bbox": [
      144.52166748046875,
      372.5148620605469,
      520.0160522460938,
      395.39990234375
    ],
    "extraction_method": "pymupdf-text-dict-sort",
    "extraction_confidence": "high",
    "page_no": 1
  },
  {
    "evidence_id": "EVD-DOC-CTX-005-00013",
    "document_id": "DOC-CTX-005",
    "page_no_or_sheet_name": 1,
    "block_order": 13,
    "block_type": "text_block",
    "text": "수송부문의 탈탄소화를 위해 동력원을 전기화하거나 친환경 연료(수",
    "bbox": [
      217.92189025878906,
      412.4312438964844,
      520.0160522460938,
      422.37042236328125
    ],
    "extraction_method": "pymupdf-text-dict-sort",
    "extraction_confidence": "high",
    "page_no": 1
  },
  {
    "evidence_id": "EVD-DOC-CTX-005-00014",
    "document_id": "DOC-CTX-005",
    "page_no_or_sheet_name": 1,
    "block_order": 14,
    "block_type": "text_block",
    "text": "친환경모빌리티",
    "bbox": [
      139.72427368164062,
      420.46246337890625,
      206.26426696777344,
      430.4016418457031
    ],
    "extraction_method": "pymupdf-text-dict-sort",
    "extraction_confidence": "high",
    "page_no": 1
  },
  {
    "evidence_id": "EVD-DOC-CTX-005-00015",
    "document_id": "DOC-CTX-005",
    "page_no_or_sheet_name": 1,
    "block_order": 15,
    "block_type": "text_block",
    "text": "소, 암모니아, e메탄올 등)를 사용하는 자동차 및 선박 구현 기술",
    "bbox": [
      217.92189025878906,
      428.3738098144531,
      500.34637451171875,
      438.31298828125
    ],
    "extraction_method": "pymupdf-text-dict-sort",
    "extraction_confidence": "high",
    "page_no": 1
  },
  {
    "evidence_id": "EVD-DOC-CTX-005-00016",
    "document_id": "DOC-CTX-005",
    "page_no_or_sheet_name": 1,
    "block_order": 16,
    "block_type": "text_block",
    "text": "자원의 순환이용성 향상을 위한 자원의 효율적 사용과 폐기물 발생",
    "bbox": [
      217.92189025878906,
      455.3443603515625,
      520.0157470703125,
      465.2835388183594
    ],
    "extraction_method": "pymupdf-text-dict-sort",
    "extraction_confidence": "high",
    "page_no": 1
  },
  {
    "evidence_id": "EVD-DOC-CTX-005-00017",
    "document_id": "DOC-CTX-005",
    "page_no_or_sheet_name": 1,
    "block_order": 17,
    "block_type": "text_block",
    "text": "기반",
    "bbox": [
      89.35157012939453,
      463.3755798339844,
      108.5187759399414,
      473.31475830078125
    ],
    "extraction_method": "pymupdf-text-dict-sort",
    "extraction_confidence": "high",
    "page_no": 1
  },
  {
    "evidence_id": "EVD-DOC-CTX-005-00018",
    "document_id": "DOC-CTX-005",
    "page_no_or_sheet_name": 1,
    "block_order": 18,
    "block_type": "text_block",
    "text": "자원순환",
    "bbox": [
      153.9965362548828,
      463.3755798339844,
      192.11285400390625,
      473.31475830078125
    ],
    "extraction_method": "pymupdf-text-dict-sort",
    "extraction_confidence": "high",
    "page_no": 1
  },
  {
    "evidence_id": "EVD-DOC-CTX-005-00019",
    "document_id": "DOC-CTX-005",
    "page_no_or_sheet_name": 1,
    "block_order": 19,
    "block_type": "text_block",
    "text": "을 감축하기 위한 재활용 및 재사용·재제조 기술",
    "bbox": [
      217.92189025878906,
      471.40679931640625,
      428.74517822265625,
      481.3459777832031
    ],
    "extraction_method": "pymupdf-text-dict-sort",
    "extraction_confidence": "high",
    "page_no": 1
  },
  {
    "evidence_id": "EVD-DOC-CTX-005-00020",
    "document_id": "DOC-CTX-005",
    "page_no_or_sheet_name": 1,
    "block_order": 20,
    "block_type": "text_block",
    "text": "기후변화 및 기후위기 예측·모니터링, 수자원의 효율적 이용, 생태계",
    "bbox": [
      217.92189025878906,
      498.2574462890625,
      523.1995239257812,
      508.1966247558594
    ],
    "extraction_method": "pymupdf-text-dict-sort",
    "extraction_confidence": "high",
    "page_no": 1
  },
  {
    "evidence_id": "EVD-DOC-CTX-005-00021",
    "document_id": "DOC-CTX-005",
    "page_no_or_sheet_name": 1,
    "block_order": 21,
    "block_type": "text_block",
    "text": "적응흡수",
    "bbox": [
      153.9965362548828,
      506.2886962890625,
      192.11285400390625,
      516.2278442382812
    ],
    "extraction_method": "pymupdf-text-dict-sort",
    "extraction_confidence": "high",
    "page_no": 1
  },
  {
    "evidence_id": "EVD-DOC-CTX-005-00022",
    "document_id": "DOC-CTX-005",
    "page_no_or_sheet_name": 1,
    "block_order": 22,
    "block_type": "text_block",
    "text": "흡수 능력 강화를 위한 제반 기술",
    "bbox": [
      217.92189025878906,
      514.3198852539062,
      365.0596923828125,
      524.259033203125
    ],
    "extraction_method": "pymupdf-text-dict-sort",
    "extraction_confidence": "high",
    "page_no": 1
  }
]