[
  {
    "document_id": "DOC-CTX-006",
    "page_no": 1,
    "page_width": 595.0,
    "page_height": 841.0,
    "blocks": [
      {
        "bbox": [
          207.60748291015625,
          160.58946228027344,
          384.7097473144531,
          173.52236938476562
        ],
        "type": "text",
        "evidence_id": "EVD-DOC-CTX-006-00001"
      },
      {
        "bbox": [
          83.59469604492188,
          187.5341033935547,
          393.5995788574219,
          198.551025390625
        ],
        "type": "text",
        "evidence_id": "EVD-DOC-CTX-006-00002"
      },
      {
        "bbox": [
          223.558837890625,
          208.3913116455078,
          523.6718139648438,
          219.40823364257812
        ],
        "type": "text",
        "evidence_id": "EVD-DOC-CTX-006-00003"
      },
      {
        "bbox": [
          164.7906951904297,
          217.26161193847656,
          186.73846435546875,
          228.27853393554688
        ],
        "type": "text",
        "evidence_id": "EVD-DOC-CTX-006-00004"
      },
      {
        "bbox": [
          223.558837890625,
          226.01205444335938,
          409.93804931640625,
          237.0289764404297
        ],
        "type": "text",
        "evidence_id": "EVD-DOC-CTX-006-00005"
      },
      {
        "bbox": [
          159.273681640625,
          246.86924743652344,
          523.5509033203125,
          266.6366271972656
        ],
        "type": "text",
        "evidence_id": "EVD-DOC-CTX-006-00006"
      },
      {
        "bbox": [
          223.558837890625,
          264.489990234375,
          476.3815002441406,
          275.5069274902344
        ],
        "type": "text",
        "evidence_id": "EVD-DOC-CTX-006-00007"
      },
      {
        "bbox": [
          87.79241943359375,
          274.6788330078125,
          109.86045837402344,
          285.6957702636719
        ],
        "type": "text",
        "evidence_id": "EVD-DOC-CTX-006-00008"
      },
      {
        "bbox": [
          223.558837890625,
          287.0253601074219,
          523.55126953125,
          298.04229736328125
        ],
        "type": "text",
        "evidence_id": "EVD-DOC-CTX-006-00009"
      },
      {
        "bbox": [
          153.7566680908203,
          295.8956604003906,
          197.7724609375,
          306.91259765625
        ],
        "type": "text",
        "evidence_id": "EVD-DOC-CTX-006-00010"
      },
      {
        "bbox": [
          223.558837890625,
          304.6460876464844,
          349.9700012207031,
          315.66302490234375
        ],
        "type": "text",
        "evidence_id": "EVD-DOC-CTX-006-00011"
      },
      {
        "bbox": [
          153.7566680908203,
          333.2947998046875,
          519.6783447265625,
          344.3117370605469
        ],
        "type": "text",
        "evidence_id": "EVD-DOC-CTX-006-00012"
      },
      {
        "bbox": [
          159.273681640625,
          360.38519287109375,
          519.8049926757812,
          380.1525573730469
        ],
        "type": "text",
        "evidence_id": "EVD-DOC-CTX-006-00013"
      },
      {
        "bbox": [
          223.558837890625,
          378.00592041015625,
          481.1792297363281,
          389.0228576660156
        ],
        "type": "text",
        "evidence_id": "EVD-DOC-CTX-006-00014"
      },
      {
        "bbox": [
          153.7566680908203,
          398.5035400390625,
          508.64434814453125,
          409.5204772949219
        ],
        "type": "text",
        "evidence_id": "EVD-DOC-CTX-006-00015"
      },
      {
        "bbox": [
          87.79241943359375,
          399.70220947265625,
          109.86045837402344,
          410.7191467285156
        ],
        "type": "text",
        "evidence_id": "EVD-DOC-CTX-006-00016"
      },
      {
        "bbox": [
          223.558837890625,
          420.1998291015625,
          523.6708374023438,
          431.2167663574219
        ],
        "type": "text",
        "evidence_id": "EVD-DOC-CTX-006-00017"
      },
      {
        "bbox": [
          153.7566680908203,
          429.07012939453125,
          197.7724609375,
          440.0870666503906
        ],
        "type": "text",
        "evidence_id": "EVD-DOC-CTX-006-00018"
      },
      {
        "bbox": [
          223.558837890625,
          437.820556640625,
          442.6800842285156,
          448.8374938964844
        ],
        "type": "text",
        "evidence_id": "EVD-DOC-CTX-006-00019"
      }
    ]
  }
]